pyroute2/__init__.py
pyroute2/arp.py
pyroute2/common.py
pyroute2/compat.py
pyroute2/conntrack.py
pyroute2/devlink.py
pyroute2/ipset.py
pyroute2/ipvs.py
pyroute2/iwutil.py
pyroute2/minimal.py
pyroute2/process.py
pyroute2/statsd.py
pyroute2/wiset.py
pyroute2/bsd/__init__.py
pyroute2/bsd/util.py
pyroute2/bsd/pf_route/__init__.py
pyroute2/bsd/pf_route/freebsd.py
pyroute2/bsd/pf_route/openbsd.py
pyroute2/bsd/rtmsocket/__init__.py
pyroute2/bsd/rtmsocket/freebsd.py
pyroute2/bsd/rtmsocket/openbsd.py
pyroute2/cli/__init__.py
pyroute2/cli/console.py
pyroute2/cli/parser.py
pyroute2/cli/server.py
pyroute2/cli/session.py
pyroute2/cli/auth/__init__.py
pyroute2/cli/auth/auth_keystone.py
pyroute2/cli/auth/auth_radius.py
pyroute2/config/__init__.py
pyroute2/config/asyncio.py
pyroute2/config/eventlet.py
pyroute2/config/log.py
pyroute2/config/test_platform.py
pyroute2/config/version.py
pyroute2/decoder/__init__.py
pyroute2/decoder/args.py
pyroute2/decoder/loader.py
pyroute2/decoder/main.py
pyroute2/dhcp/__init__.py
pyroute2/dhcp/cli.py
pyroute2/dhcp/client.py
pyroute2/dhcp/dhcp4msg.py
pyroute2/dhcp/dhcp4socket.py
pyroute2/dhcp/fsm.py
pyroute2/dhcp/hooks.py
pyroute2/dhcp/iface_status.py
pyroute2/dhcp/leases.py
pyroute2/dhcp/messages.py
pyroute2/dhcp/server_detector.py
pyroute2/dhcp/timers.py
pyroute2/dhcp/xids.py
pyroute2/dhcp/enums/__init__.py
pyroute2/dhcp/enums/bootp.py
pyroute2/dhcp/enums/dhcp.py
pyroute2/ethtool/__init__.py
pyroute2/ethtool/common.py
pyroute2/ethtool/ethtool.py
pyroute2/ethtool/ioctl.py
pyroute2/ext/__init__.py
pyroute2/ext/bpf.py
pyroute2/ext/icmp.py
pyroute2/ext/rawsocket.py
pyroute2/fixtures/__init__.py
pyroute2/fixtures/doctest.py
pyroute2/fixtures/iproute.py
pyroute2/fixtures/plan9.py
pyroute2/inotify/__init__.py
pyroute2/inotify/inotify_fd.py
pyroute2/inotify/inotify_msg.py
pyroute2/ipdb/__init__.py
pyroute2/iproute/__init__.py
pyroute2/iproute/bsd.py
pyroute2/iproute/ipmock.py
pyroute2/iproute/linux.py
pyroute2/iproute/parsers.py
pyroute2-0.9.1.dist-info/licenses/LICENSE
pyroute2-0.9.1.dist-info/licenses/LICENSE.Apache-2.0
pyroute2-0.9.1.dist-info/licenses/LICENSE.GPL-2.0-or-later
pyroute2-0.9.1.dist-info/METADATA
pyroute2-0.9.1.dist-info/WHEEL
pyroute2-0.9.1.dist-info/entry_points.txt
pyroute2-0.9.1.dist-info/top_level.txt
pyroute2-0.9.1.dist-info/RECORD
