Metadata-Version: 2.4
Name: pyroute2
Version: 0.9.1
Summary: Python Netlink library
Home-page: https://github.com/svinota/pyroute2
Author: Peter Saveliev
Author-email: peter@svinota.eu
License: GPL-2.0-or-later OR Apache-2.0
Classifier: License :: OSI Approved :: GNU General Public License v2 or later (GPLv2+)
Classifier: License :: OSI Approved :: Apache Software License
Classifier: Programming Language :: Python
Classifier: Topic :: Software Development :: Libraries :: Python Modules
Classifier: Topic :: System :: Networking
Classifier: Topic :: System :: Systems Administration
Classifier: Operating System :: POSIX :: Linux
Classifier: Intended Audience :: Developers
Classifier: Intended Audience :: System Administrators
Classifier: Intended Audience :: Telecommunications Industry
Classifier: Programming Language :: Python :: 3
Classifier: Programming Language :: Python :: 3.9
Classifier: Programming Language :: Python :: 3.10
Classifier: Programming Language :: Python :: 3.11
Classifier: Programming Language :: Python :: 3.12
Classifier: Programming Language :: Python :: 3.13
Classifier: Programming Language :: Python :: 3.14
Classifier: Development Status :: 4 - Beta
License-File: LICENSE
License-File: LICENSE.Apache-2.0
License-File: LICENSE.GPL-2.0-or-later
Requires-Dist: win_inet_pton; platform_system == "Windows"
Dynamic: license-file
